{
  "generated_at": "2026-05-22T09:00:00+02:00",
  "agent": "pipeline-scan",
  "schema_version": "1.0",
  "deals": {
    "006VT00000nNpjzYAC": {
      "account_name": "BNP Paribas",
      "opportunity_name": "BNP Paribas FRANCE - Apex - 2026",
      "stage": "5 - Navigating/MAP",
      "ai_health_score": 6.5,
      "meddpicc_scores": {
        "metrics": 8.0,
        "economic_buyer": 3.3,
        "decision_criteria": 6.0,
        "decision_process": 5.3,
        "paper_process": 0.0,
        "pain": 7.3,
        "champion": 7.5,
        "competition": 3.9
      },
      "signals": {
        "deal_velocity": "Accelerating",
        "champion_engagement": "Active",
        "economic_buyer_status": "Identified",
        "metrics_validation": "Partial",
        "procurement_status": "Not_Started",
        "client_timeline": "\"Group CyberMonitoring meeting done, commercial proposal being sent\" (May 18, Calendar)",
        "engagement_7d": 5,
        "engagement_30d": 18,
        "score_wow_delta": 0.0
      },
      "next_step": "May 22 \u2014 send group-level proposal to Fangouse",
      "next_step_date": "2026-05-22",
      "red_flags": "No EB confirmed \u00b7 Paper process 0% \u00b7 Group-level buy-in unproven"
    },
    "006VT00000qEkbJYAS": {
      "account_name": "BNP Paribas Fortis",
      "opportunity_name": "BNP Paribas Fortis - Apex - NB 26",
      "stage": "2 - Qualifying",
      "ai_health_score": 3.1,
      "meddpicc_scores": {
        "metrics": 3.3,
        "economic_buyer": 2.0,
        "decision_criteria": 3.3,
        "decision_process": 2.7,
        "paper_process": 0.0,
        "pain": 2.3,
        "champion": 5.8,
        "competition": 1.7
      },
      "signals": {
        "deal_velocity": "Steady",
        "champion_engagement": "Active",
        "economic_buyer_status": "Unknown",
        "metrics_validation": "Partial",
        "procurement_status": "Not_Started",
        "client_timeline": "\"20 additional accounts then follow-up\" (May 20, Granola)",
        "engagement_7d": 3,
        "engagement_30d": 8,
        "score_wow_delta": 0.0
      },
      "next_step": "May 22 \u2014 send 20 additional accounts",
      "next_step_date": "2026-05-22",
      "red_flags": "40% validation rate \u00b7 Detection after internal alerts \u00b7 No EB"
    },
    "006VT00000pcfuPYAQ": {
      "account_name": "Intesa Sanpaolo",
      "opportunity_name": "Intesa Sanpaolo - Apex - NB 2026",
      "stage": "2 - Qualifying",
      "ai_health_score": 2.8,
      "meddpicc_scores": {
        "metrics": 3.3,
        "economic_buyer": 0.0,
        "decision_criteria": 2.7,
        "decision_process": 2.0,
        "paper_process": 0.0,
        "pain": 2.7,
        "champion": 5.0,
        "competition": 1.7
      },
      "signals": {
        "deal_velocity": "Steady",
        "champion_engagement": "Active",
        "economic_buyer_status": "Unknown",
        "metrics_validation": "Pitch_Only",
        "procurement_status": "Not_Started",
        "client_timeline": "\"Follow-up June 3 to review test results\" (May 20, Granola)",
        "engagement_7d": 3,
        "engagement_30d": 3,
        "score_wow_delta": 0.0
      },
      "next_step": "Jun 3 \u2014 review 20-account test results with Gianluca",
      "next_step_date": "2026-06-03",
      "red_flags": "First meeting only \u00b7 No EB \u00b7 No procurement discussion"
    },
    "006VT00000nO5dRYAS": {
      "account_name": "Credit Agricole",
      "opportunity_name": "Credit Agricole - Apex - 2026",
      "stage": "2 - Qualifying",
      "ai_health_score": 2.3,
      "meddpicc_scores": {
        "metrics": 4.0,
        "economic_buyer": 1.3,
        "decision_criteria": 2.0,
        "decision_process": 2.0,
        "paper_process": 0.0,
        "pain": 2.3,
        "champion": 3.3,
        "competition": 1.1
      },
      "signals": {
        "deal_velocity": "Slowing",
        "champion_engagement": "Passive",
        "economic_buyer_status": "Unknown",
        "metrics_validation": "Partial",
        "procurement_status": "Not_Started",
        "client_timeline": "\"Next meeting Jun 18\" (May 18, Granola)",
        "engagement_7d": 1,
        "engagement_30d": 4,
        "score_wow_delta": 0.0
      },
      "next_step": "Jun 18 \u2014 next review with Sgonidec",
      "next_step_date": "2026-06-18",
      "red_flags": "CAPS unresponsive \u00b7 MISP competitor \u00b7 No EB \u00b7 27-day gap"
    },
    "006VT00000obYKTYA2": {
      "account_name": "BPCE",
      "opportunity_name": "BPCE - Apex - 2026",
      "stage": "3 - AVT",
      "ai_health_score": 3.2,
      "meddpicc_scores": {
        "metrics": 4.0,
        "economic_buyer": 1.3,
        "decision_criteria": 2.7,
        "decision_process": 2.7,
        "paper_process": 0.0,
        "pain": 2.7,
        "champion": 5.8,
        "competition": 1.7
      },
      "signals": {
        "deal_velocity": "Slowing",
        "champion_engagement": "Passive",
        "economic_buyer_status": "Unknown",
        "metrics_validation": "Partial",
        "procurement_status": "Not_Started",
        "client_timeline": "\"Jun 19 rescheduled meeting\" (May 18, Gmail)",
        "engagement_7d": 2,
        "engagement_30d": 6,
        "score_wow_delta": 0.0
      },
      "next_step": "Jun 19 \u2014 external IBAN analysis readout",
      "next_step_date": "2026-06-19",
      "red_flags": "4-week slip \u00b7 No EB \u00b7 No budget owner"
    },
    "006VT00000nNzg7YAC": {
      "account_name": "Swan",
      "opportunity_name": "Swan - Apex - 2026",
      "stage": "3 - AVT",
      "ai_health_score": 3.0,
      "meddpicc_scores": {
        "metrics": 4.0,
        "economic_buyer": 1.3,
        "decision_criteria": 2.7,
        "decision_process": 2.7,
        "paper_process": 0.0,
        "pain": 2.0,
        "champion": 5.8,
        "competition": 1.7
      },
      "signals": {
        "deal_velocity": "Steady",
        "champion_engagement": "Active",
        "economic_buyer_status": "Unknown",
        "metrics_validation": "Partial",
        "procurement_status": "Not_Started",
        "client_timeline": null,
        "engagement_7d": 1,
        "engagement_30d": 4,
        "score_wow_delta": 0.0
      },
      "next_step": "May 22 \u2014 2nd restitution (15:00 today)",
      "next_step_date": "2026-05-22",
      "red_flags": "No EB \u00b7 No procurement discussion"
    },
    "006VT00000pmk6PYAQ": {
      "account_name": "BGL BNP Paribas",
      "opportunity_name": "BGL (BNP Luxembourg) - Apex - NB27",
      "stage": "3 - AVT",
      "ai_health_score": 3.1,
      "meddpicc_scores": {
        "metrics": 3.3,
        "economic_buyer": 1.3,
        "decision_criteria": 2.7,
        "decision_process": 2.7,
        "paper_process": 0.0,
        "pain": 2.3,
        "champion": 5.8,
        "competition": 1.7
      },
      "signals": {
        "deal_velocity": "Steady",
        "champion_engagement": "Active",
        "economic_buyer_status": "Unknown",
        "metrics_validation": "Pitch_Only",
        "procurement_status": "Not_Started",
        "client_timeline": null,
        "engagement_7d": 1,
        "engagement_30d": 3,
        "score_wow_delta": 0.0
      },
      "next_step": "May 22 \u2014 POC kickoff (16:00 today)",
      "next_step_date": "2026-05-22",
      "red_flags": "Early stage \u00b7 No EB"
    },
    "006VT00000pCwqrYAC": {
      "account_name": "UniCredit",
      "opportunity_name": "UniCredit - Apex - NB 2026",
      "stage": "3 - AVT",
      "ai_health_score": 3.3,
      "meddpicc_scores": {
        "metrics": 4.0,
        "economic_buyer": 1.3,
        "decision_criteria": 3.3,
        "decision_process": 3.3,
        "paper_process": 0.0,
        "pain": 2.3,
        "champion": 5.8,
        "competition": 1.7
      },
      "signals": {
        "deal_velocity": "Steady",
        "champion_engagement": "Active",
        "economic_buyer_status": "Identified",
        "metrics_validation": "Partial",
        "procurement_status": "Not_Started",
        "client_timeline": "\"DPO Q&A May 29\" (Calendar)",
        "engagement_7d": 0,
        "engagement_30d": 5,
        "score_wow_delta": 0.0
      },
      "next_step": "May 29 \u2014 Data Protection Q&A",
      "next_step_date": "2026-05-29",
      "red_flags": "DPO gate blocking \u00b7 No procurement"
    },
    "006VT00000o6Ul2YAE": {
      "account_name": "CGD",
      "opportunity_name": "CGD - Apex - 2026",
      "stage": "4 - Negotiating",
      "ai_health_score": 4.7,
      "meddpicc_scores": {
        "metrics": 6.0,
        "economic_buyer": 2.7,
        "decision_criteria": 4.7,
        "decision_process": 4.0,
        "paper_process": 3.3,
        "pain": 4.0,
        "champion": 7.5,
        "competition": 1.7
      },
      "signals": {
        "deal_velocity": "Slowing",
        "champion_engagement": "Passive",
        "economic_buyer_status": "Identified",
        "metrics_validation": "Full_Analysis",
        "procurement_status": "Discussed",
        "client_timeline": "\"Board approved, procurement to follow\" (Apr 30)",
        "engagement_7d": 1,
        "engagement_30d": 5,
        "score_wow_delta": 0.0
      },
      "next_step": "May 22 \u2014 chase Manuel on procurement",
      "next_step_date": "2026-05-22",
      "red_flags": "Procurement stalled 9+ days \u00b7 Manuel unresponsive"
    },
    "006VT00000nO329YAC": {
      "account_name": "Belfius",
      "opportunity_name": "Belfius - Apex - 2026",
      "stage": "3 - AVT",
      "ai_health_score": 1.2,
      "meddpicc_scores": {
        "metrics": 1.3,
        "economic_buyer": 0.0,
        "decision_criteria": 1.3,
        "decision_process": 1.3,
        "paper_process": 0.0,
        "pain": 1.0,
        "champion": 1.7,
        "competition": 0.6
      },
      "signals": {
        "deal_velocity": "Stalled",
        "champion_engagement": "None",
        "economic_buyer_status": "Unknown",
        "metrics_validation": "None",
        "procurement_status": "Not_Started",
        "client_timeline": null,
        "engagement_7d": 0,
        "engagement_30d": 1,
        "score_wow_delta": 0.0
      },
      "next_step": "May 28 \u2014 ISABEL/Belfius meeting",
      "next_step_date": "2026-05-28",
      "red_flags": "Score 1.2/10 \u00b7 No champion \u00b7 No EB \u00b7 First real engagement"
    },
    "006VT00000oNKakYAG": {
      "account_name": "Incore Bank",
      "opportunity_name": "Incore - Apex - 2026",
      "stage": "3 - AVT",
      "ai_health_score": 0.5,
      "meddpicc_scores": {
        "metrics": 0.7,
        "economic_buyer": 0.0,
        "decision_criteria": 0.7,
        "decision_process": 0.7,
        "paper_process": 0.0,
        "pain": 0.3,
        "champion": 0.8,
        "competition": 0.0
      },
      "signals": {
        "deal_velocity": "Dark",
        "champion_engagement": "Identified_Only",
        "economic_buyer_status": "Unknown",
        "metrics_validation": "None",
        "procurement_status": "Not_Started",
        "client_timeline": null,
        "engagement_7d": 0,
        "engagement_30d": 0,
        "score_wow_delta": 0.0
      },
      "next_step": "May 29 \u2014 catch-up with Thomas Glaus",
      "next_step_date": "2026-05-29",
      "red_flags": "Very early stage \u00b7 Minimal engagement"
    },
    "006VT00000pmi1OYAQ": {
      "account_name": "Banca Profilo",
      "opportunity_name": "Banca Profilo - Apex - NB 27",
      "stage": "2 - Qualifying",
      "ai_health_score": 2.5,
      "meddpicc_scores": {
        "metrics": 2.7,
        "economic_buyer": 0.0,
        "decision_criteria": 2.0,
        "decision_process": 2.0,
        "paper_process": 0.0,
        "pain": 2.0,
        "champion": 4.2,
        "competition": 1.1
      },
      "signals": {
        "deal_velocity": "Steady",
        "champion_engagement": "Active",
        "economic_buyer_status": "Unknown",
        "metrics_validation": "Pitch_Only",
        "procurement_status": "Not_Started",
        "client_timeline": null,
        "engagement_7d": 1,
        "engagement_30d": 2,
        "score_wow_delta": 0.0
      },
      "next_step": "May 22 \u2014 1st analysis readout (10:00 today)",
      "next_step_date": "2026-05-22",
      "red_flags": "Early stage \u00b7 No EB"
    }
  }
}